setup.cfg
setup.py
examples/__init__.py
examples/handlers/__init__.py
examples/handlers/country_handler.py
examples/handlers/save_tweet_handler.py
responsebot/__init__.py
responsebot/models.py
responsebot/responsebot.py
responsebot/responsebot_client.py
responsebot/responsebot_stream.py
responsebot/start_responsebot.py
responsebot.egg-info/PKG-INFO
responsebot.egg-info/SOURCES.txt
responsebot.egg-info/dependency_links.txt
responsebot.egg-info/entry_points.txt
responsebot.egg-info/requires.txt
responsebot.egg-info/top_level.txt
responsebot/common/__init__.py
responsebot/common/constants.py
responsebot/common/exceptions.py
responsebot/handlers/__init__.py
responsebot/handlers/base.py
responsebot/handlers/event.py
responsebot/listeners/__init__.py
responsebot/listeners/responsebot_listener.py
responsebot/listeners/tweepy_wrapper_listener.py
responsebot/utils/__init__.py
responsebot/utils/auth_utils.py
responsebot/utils/config_utils.py
responsebot/utils/handler_utils.py
responsebot/utils/log_utils.py
responsebot/utils/tweepy.py
tests/common/__init__.py
tests/common/exception.py
tests/common/utils.py
tests/examples/__init__.py
tests/examples/handlers/__init__.py
tests/examples/handlers/test_country_handler.py
tests/examples/handlers/test_save_tweet_handler.py
tests/integration_tests/__init__.py
tests/integration_tests/test_start_responsebot_command.py
tests/unit_tests/__init__.py
tests/unit_tests/test_responsebot.py
tests/unit_tests/test_tweet_client.py
tests/unit_tests/test_tweet_stream.py
tests/unit_tests/handlers/__init__.py
tests/unit_tests/handlers/test_base.py
tests/unit_tests/handlers/test_event.py
tests/unit_tests/listeners/__init__.py
tests/unit_tests/listeners/test_responsebot_listener.py
tests/unit_tests/listeners/test_tweepy_wrapper_listener.py
tests/unit_tests/models/__init__.py
tests/unit_tests/models/test_event_model.py
tests/unit_tests/models/test_list_model.py
tests/unit_tests/models/test_tweet_filter_model.py
tests/unit_tests/models/test_tweet_model.py
tests/unit_tests/models/test_user_model.py
tests/unit_tests/utils/__init__.py
tests/unit_tests/utils/test_auth_utils.py
tests/unit_tests/utils/test_config_utils.py
tests/unit_tests/utils/test_handler_utils.py
