Metadata-Version: 1.0
Name: responsebot
Version: 0.4.0
Summary: Automatically response to any tweets mentioning you
Home-page: https://github.com/invinst/ResponseBot
Author: Invisible Institute
Author-email: dev@invisibleinstitute.com
License: UNKNOWN
Platform: UNKNOWN
